README.rst
setup.py
data_exporter/__init__.py
data_exporter/base.py
data_exporter/channels.py
data_exporter/models.py
data_exporter/settings.py
data_exporter/signals.py
data_exporter/tasks.py
data_exporter/views.py
data_exporter/tests/__init__.py
data_exporter/tests/exports.py
data_exporter/tests/models.py
data_exporter/tests/settings.py
django_data_exporter.egg-info/PKG-INFO
django_data_exporter.egg-info/SOURCES.txt
django_data_exporter.egg-info/dependency_links.txt
django_data_exporter.egg-info/not-zip-safe
django_data_exporter.egg-info/top_level.txt