Metadata-Version: 1.0
Name: django-data-exporter
Version: 0.1.5
Summary: Export asynchronously your data from your Django models
Home-page: http://github.com/thoas/django-data-exporter
Author: Florent Messa
Author-email: florent.messa@gmail.com
License: UNKNOWN
Platform: UNKNOWN
Classifier: Environment :: Web Environment
Classifier: Intended Audience :: Developers
Classifier: License :: OSI Approved :: MIT License
Classifier: Operating System :: OS Independent
Classifier: Programming Language :: Python
Classifier: Topic :: Utilities
